qstrbuilder/__init__.py
qstrbuilder/version.py
qstrbuilder-0.1.0.dist-info/METADATA
qstrbuilder-0.1.0.dist-info/WHEEL
qstrbuilder-0.1.0.dist-info/top_level.txt
qstrbuilder-0.1.0.dist-info/RECORD
