Metadata-Version: 2.1
Name: qstrbuilder
Version: 0.1.0
Summary: qstrbuilder
Home-page: http://github.com/qstrbuilder/qstrbuilder/
Author: Zhiqing Xiao
Author-email: xzq.xiaozhiqing@gmail.com
Classifier: Programming Language :: Python
Classifier: Intended Audience :: Science/Research
